k9_analysis/ReportingEffort.py
k9_analysis/__init__.py
k9_analysis/count_burrows_detection.py
k9_analysis/group_effort_and_distance.py
k9_analysis/write_maya_nests_table.py
k9_analysis-0.6.0.dist-info/LICENSE
k9_analysis-0.6.0.dist-info/WHEEL
k9_analysis-0.6.0.dist-info/METADATA
k9_analysis-0.6.0.dist-info/RECORD
