Metadata-Version: 2.1
Name: k9_analysis
Version: 0.6.0
Summary: A module to do analyses of k9 data
Home-page: https://github.com/IslasGECI/k9_analysis
Author: Ciencia de Datos • GECI
Author-email: ciencia.datos@islas.org.mx
Requires-Python: >=3.9
Classifier: License :: OSI Approved :: GNU General Public License v3 or later (GPLv3+)
Requires-Dist: pandas
